Yihui/__init__.py
Yihui/__init__1.py
Yihui/binning.py
Yihui/binning1.py
Yihui/binning_funciton.py
Yihui/cluster.py
Yihui/data_processing.py
Yihui/dataprocessing.py
Yihui/eda.py
Yihui/main.py
Yihui/test.py
Yihui/var_selelct.py
Yihui/yihui.py
Yihui-0.1.8.dist-info/METADATA
Yihui-0.1.8.dist-info/WHEEL
Yihui-0.1.8.dist-info/top_level.txt
Yihui-0.1.8.dist-info/RECORD
