Metadata-Version: 2.1
Name: Yihui
Version: 0.1.8
Summary: Package for Logistic Regression Modeling, focus on Credit Risk Management
Home-page: https://github.com/encyc/yihui
Author: encyc
Author-email: atomyuangao@gmail.com
Classifier: Programming Language :: Python :: 3
Classifier: License :: OSI Approved :: MIT License
Classifier: Operating System :: OS Independent
Requires-Python: >=3.6
Requires-Dist: pandas
Requires-Dist: numpy
Requires-Dist: matplotlib
Requires-Dist: seaborn
Requires-Dist: scikit-learn
Requires-Dist: ydata-profiling ==4.6.3
